rbmotd/__init__.py
rbmotd/admin_urls.py
rbmotd/extension.py
rbmotd/forms.py
rbmotd/static/staticfiles.json
rbmotd/static/css/default.min.3724a4f79a3e.css
rbmotd/static/css/default.min.c58185b08744.css
rbmotd/static/css/default.min.css
rbmotd/static/css/motd.12f29e14a8b3.less
rbmotd/static/css/motd.css
rbmotd/static/css/motd.css.map
rbmotd/static/css/motd.less
rbmotd/templates/rbmotd/motd.html
rbmotd-3.0.1.dist-info/AUTHORS
rbmotd-3.0.1.dist-info/LICENSE
rbmotd-3.0.1.dist-info/METADATA
rbmotd-3.0.1.dist-info/WHEEL
rbmotd-3.0.1.dist-info/entry_points.txt
rbmotd-3.0.1.dist-info/top_level.txt
rbmotd-3.0.1.dist-info/RECORD
